securenv/__init__.py
securenv/cli.py
securenv/tcss/exit_screen.tcss
securenv/tcss/main_screen.tcss
securenv-0.0.5.dist-info/LICENSE
securenv-0.0.5.dist-info/METADATA
securenv-0.0.5.dist-info/WHEEL
securenv-0.0.5.dist-info/entry_points.txt
securenv-0.0.5.dist-info/top_level.txt
securenv-0.0.5.dist-info/RECORD
