Metadata-Version: 2.1
Name: securenv
Version: 0.0.5
Summary: Simple TUI for Defining and Constraining Environment Variables
Home-page: https://github.com/TheDrowsyDev/securenv
Author: DrowsyDev
License: Apache-2.0
Project-URL: Documentation, https://github.com/TheDrowsyDev/securenv/blob/main/README.md
Project-URL: Source, https://github.com/TheDrowsyDev/securenv
Classifier: Development Status :: 3 - Alpha
Classifier: Environment :: Console
Classifier: Topic :: Utilities
Classifier: Intended Audience :: Developers
Classifier: Programming Language :: Python :: 3.8
Classifier: Programming Language :: Python :: 3.9
Classifier: Programming Language :: Python :: 3.10
Classifier: Programming Language :: Python :: 3.11
Classifier: Programming Language :: Python :: 3.12
Requires-Python: >=3.8
License-File: LICENSE
Requires-Dist: textual
Requires-Dist: PyYaml
Requires-Dist: python-dotenv
Requires-Dist: schema
